{
  "hashtag": "cinemanv6",
  "start_time": "2025-11-01T10:45:05.874607",
  "pages": [
    {
      "page_number": 1,
      "request_data": {
        "max_id": null,
        "decoded_max_id": null,
        "page": null
      },
      "response": {
        "sections_count": 0,
        "more_available": true,
        "next_max_id": "e0b416e27679405986fa5090c4cc8ba0",
        "next_page": 1,
        "status": "ok"
      },
      "received_media_ids": [],
      "fetched_via_media_info": [],
      "raw_media_samples": [],
      "timestamp": "2025-11-01T10:45:11.947749"
    },
    {
      "page_number": 2,
      "request_data": {
        "max_id": "WyJlMGI0MTZlMjc2Nzk0MDU5ODZmYTUwOTBjNGNjOGJhMCJd",
        "decoded_max_id": "e0b416e27679405986fa5090c4cc8ba0",
        "page": 1
      },
      "response": {
        "sections_count": 1,
        "more_available": true,
        "next_max_id": "e0b416e27679405986fa5090c4cc8ba0",
        "next_page": 2,
        "status": "ok"
      },
      "received_media_ids": [
        "DQaD92FjPMu",
        "DQemQmgjLxA"
      ],
      "fetched_via_media_info": [],
      "raw_media_samples": [
        {
          "media_type": 2,
          "pk": 3754330683469525806,
          "id": "3754330683469525806_78243770695",
          "has_play_count": true,
          "has_view_count": false,
          "has_video_view_count": false,
          "play_count": 0,
          "view_count": null,
          "video_view_count": null
        },
        {
          "media_type": 2,
          "pk": 3755607405900905536,
          "id": "3755607405900905536_77719357247",
          "has_play_count": true,
          "has_view_count": false,
          "has_video_view_count": false,
          "play_count": 265,
          "view_count": null,
          "video_view_count": null
        }
      ],
      "timestamp": "2025-11-01T10:45:21.344968"
    },
    {
      "page_number": 3,
      "request_data": {
        "max_id": "WyJlMGI0MTZlMjc2Nzk0MDU5ODZmYTUwOTBjNGNjOGJhMCJd",
        "decoded_max_id": "e0b416e27679405986fa5090c4cc8ba0",
        "page": 2
      },
      "response": {
        "sections_count": 0,
        "more_available": false,
        "next_max_id": null,
        "next_page": null,
        "status": "ok"
      },
      "received_media_ids": [],
      "fetched_via_media_info": [],
      "raw_media_samples": [],
      "timestamp": "2025-11-01T10:45:34.593867"
    },
    {
      "page_number": 4,
      "request_data": {
        "max_id": null,
        "decoded_max_id": null,
        "page": null
      },
      "response": {
        "sections_count": 0,
        "more_available": true,
        "next_max_id": "b9c9176aa2f14b16bfe3f6d4f69e2174",
        "next_page": 1,
        "status": "ok"
      },
      "received_media_ids": [],
      "fetched_via_media_info": [],
      "raw_media_samples": [],
      "timestamp": "2025-11-01T10:45:40.551895"
    },
    {
      "page_number": 5,
      "request_data": {
        "max_id": "WyJiOWM5MTc2YWEyZjE0YjE2YmZlM2Y2ZDRmNjllMjE3NCJd",
        "decoded_max_id": "b9c9176aa2f14b16bfe3f6d4f69e2174",
        "page": 1
      },
      "response": {
        "sections_count": 1,
        "more_available": true,
        "next_max_id": "b9c9176aa2f14b16bfe3f6d4f69e2174",
        "next_page": 2,
        "status": "ok"
      },
      "received_media_ids": [
        "DQdkqPgjF6Q",
        "DQegN0KDBrF",
        "DQeI3lHDOri"
      ],
      "fetched_via_media_info": [],
      "raw_media_samples": [
        {
          "media_type": 2,
          "pk": 3755318896841481872,
          "id": "3755318896841481872_77714830141",
          "has_play_count": true,
          "has_view_count": false,
          "has_video_view_count": false,
          "play_count": 2,
          "view_count": null,
          "video_view_count": null
        },
        {
          "media_type": 2,
          "pk": 3755580826118265541,
          "id": "3755580826118265541_77910746512",
          "has_play_count": true,
          "has_view_count": false,
          "has_video_view_count": false,
          "play_count": 0,
          "view_count": null,
          "video_view_count": null
        }
      ],
      "timestamp": "2025-11-01T10:45:49.532164"
    },
    {
      "page_number": 6,
      "request_data": {
        "max_id": "WyJiOWM5MTc2YWEyZjE0YjE2YmZlM2Y2ZDRmNjllMjE3NCJd",
        "decoded_max_id": "b9c9176aa2f14b16bfe3f6d4f69e2174",
        "page": 2
      },
      "response": {
        "sections_count": 1,
        "more_available": true,
        "next_max_id": "b9c9176aa2f14b16bfe3f6d4f69e2174",
        "next_page": 3,
        "status": "ok"
      },
      "received_media_ids": [],
      "fetched_via_media_info": [],
      "raw_media_samples": [
        {
          "media_type": 2,
          "pk": 3754330683469525806,
          "id": "3754330683469525806_78243770695",
          "has_play_count": true,
          "has_view_count": false,
          "has_video_view_count": false,
          "play_count": 0,
          "view_count": null,
          "video_view_count": null
        },
        {
          "media_type": 2,
          "pk": 3755607405900905536,
          "id": "3755607405900905536_77719357247",
          "has_play_count": true,
          "has_view_count": false,
          "has_video_view_count": false,
          "play_count": 265,
          "view_count": null,
          "video_view_count": null
        }
      ],
      "timestamp": "2025-11-01T10:46:15.679774"
    },
    {
      "page_number": 7,
      "request_data": {
        "max_id": "WyJiOWM5MTc2YWEyZjE0YjE2YmZlM2Y2ZDRmNjllMjE3NCJd",
        "decoded_max_id": "b9c9176aa2f14b16bfe3f6d4f69e2174",
        "page": 3
      },
      "response": {
        "sections_count": 1,
        "more_available": true,
        "next_max_id": "b9c9176aa2f14b16bfe3f6d4f69e2174",
        "next_page": 4,
        "status": "ok"
      },
      "received_media_ids": [],
      "fetched_via_media_info": [],
      "raw_media_samples": [
        {
          "media_type": 2,
          "pk": 3754330683469525806,
          "id": "3754330683469525806_78243770695",
          "has_play_count": true,
          "has_view_count": false,
          "has_video_view_count": false,
          "play_count": 0,
          "view_count": null,
          "video_view_count": null
        },
        {
          "media_type": 2,
          "pk": 3755607405900905536,
          "id": "3755607405900905536_77719357247",
          "has_play_count": true,
          "has_view_count": false,
          "has_video_view_count": false,
          "play_count": 265,
          "view_count": null,
          "video_view_count": null
        }
      ],
      "timestamp": "2025-11-01T10:46:24.355836"
    },
    {
      "page_number": 8,
      "request_data": {
        "max_id": "WyJiOWM5MTc2YWEyZjE0YjE2YmZlM2Y2ZDRmNjllMjE3NCJd",
        "decoded_max_id": "b9c9176aa2f14b16bfe3f6d4f69e2174",
        "page": 4
      },
      "response": {
        "sections_count": 0,
        "more_available": false,
        "next_max_id": null,
        "next_page": null,
        "status": "ok"
      },
      "received_media_ids": [],
      "fetched_via_media_info": [],
      "raw_media_samples": [],
      "timestamp": "2025-11-01T10:46:32.503650"
    },
    {
      "page_number": 9,
      "request_data": {
        "max_id": null,
        "decoded_max_id": null,
        "page": null
      },
      "response": {
        "sections_count": 0,
        "more_available": true,
        "next_max_id": "19d8869f0e3a493fb1d14bfd91e70e59",
        "next_page": 1,
        "status": "ok"
      },
      "received_media_ids": [],
      "fetched_via_media_info": [],
      "raw_media_samples": [],
      "timestamp": "2025-11-01T10:46:38.241801"
    },
    {
      "page_number": 10,
      "request_data": {
        "max_id": "WyIxOWQ4ODY5ZjBlM2E0OTNmYjFkMTRiZmQ5MWU3MGU1OSJd",
        "decoded_max_id": "19d8869f0e3a493fb1d14bfd91e70e59",
        "page": 1
      },
      "response": {
        "sections_count": 1,
        "more_available": true,
        "next_max_id": "19d8869f0e3a493fb1d14bfd91e70e59",
        "next_page": 2,
        "status": "ok"
      },
      "received_media_ids": [],
      "fetched_via_media_info": [],
      "raw_media_samples": [
        {
          "media_type": 2,
          "pk": 3754330683469525806,
          "id": "3754330683469525806_78243770695",
          "has_play_count": true,
          "has_view_count": false,
          "has_video_view_count": false,
          "play_count": 0,
          "view_count": null,
          "video_view_count": null
        },
        {
          "media_type": 2,
          "pk": 3755607405900905536,
          "id": "3755607405900905536_77719357247",
          "has_play_count": true,
          "has_view_count": false,
          "has_video_view_count": false,
          "play_count": 265,
          "view_count": null,
          "video_view_count": null
        }
      ],
      "timestamp": "2025-11-01T10:46:46.924426"
    },
    {
      "page_number": 11,
      "request_data": {
        "max_id": "WyIxOWQ4ODY5ZjBlM2E0OTNmYjFkMTRiZmQ5MWU3MGU1OSJd",
        "decoded_max_id": "19d8869f0e3a493fb1d14bfd91e70e59",
        "page": 2
      },
      "response": {
        "sections_count": 0,
        "more_available": false,
        "next_max_id": null,
        "next_page": null,
        "status": "ok"
      },
      "received_media_ids": [],
      "fetched_via_media_info": [],
      "raw_media_samples": [],
      "timestamp": "2025-11-01T10:47:13.164864"
    },
    {
      "page_number": 12,
      "request_data": {
        "max_id": null,
        "decoded_max_id": null,
        "page": 2
      },
      "response": {
        "sections_count": 0,
        "more_available": true,
        "next_max_id": "bd4b4ecaa5944bc686b716013bf418ba",
        "next_page": 1,
        "status": "ok"
      },
      "received_media_ids": [],
      "fetched_via_media_info": [],
      "raw_media_samples": [],
      "timestamp": "2025-11-01T10:47:21.848746"
    },
    {
      "page_number": 13,
      "request_data": {
        "max_id": "WyJiZDRiNGVjYWE1OTQ0YmM2ODZiNzE2MDEzYmY0MThiYSJd",
        "decoded_max_id": "bd4b4ecaa5944bc686b716013bf418ba",
        "page": 1
      },
      "response": {
        "sections_count": 1,
        "more_available": true,
        "next_max_id": "bd4b4ecaa5944bc686b716013bf418ba",
        "next_page": 2,
        "status": "ok"
      },
      "received_media_ids": [],
      "fetched_via_media_info": [],
      "raw_media_samples": [
        {
          "media_type": 2,
          "pk": 3754330683469525806,
          "id": "3754330683469525806_78243770695",
          "has_play_count": true,
          "has_view_count": false,
          "has_video_view_count": false,
          "play_count": 0,
          "view_count": null,
          "video_view_count": null
        },
        {
          "media_type": 2,
          "pk": 3755607405900905536,
          "id": "3755607405900905536_77719357247",
          "has_play_count": true,
          "has_view_count": false,
          "has_video_view_count": false,
          "play_count": 265,
          "view_count": null,
          "video_view_count": null
        }
      ],
      "timestamp": "2025-11-01T10:47:30.696279"
    },
    {
      "page_number": 14,
      "request_data": {
        "max_id": "WyJiZDRiNGVjYWE1OTQ0YmM2ODZiNzE2MDEzYmY0MThiYSJd",
        "decoded_max_id": "bd4b4ecaa5944bc686b716013bf418ba",
        "page": 2
      },
      "response": {
        "sections_count": 0,
        "more_available": false,
        "next_max_id": null,
        "next_page": null,
        "status": "ok"
      },
      "received_media_ids": [],
      "fetched_via_media_info": [],
      "raw_media_samples": [],
      "timestamp": "2025-11-01T10:47:38.978156"
    },
    {
      "page_number": 15,
      "request_data": {
        "max_id": null,
        "decoded_max_id": null,
        "page": 2
      },
      "response": {
        "sections_count": 0,
        "more_available": true,
        "next_max_id": "ebee0bd0b9a647ba83152f03e121115a",
        "next_page": 1,
        "status": "ok"
      },
      "received_media_ids": [],
      "fetched_via_media_info": [],
      "raw_media_samples": [],
      "timestamp": "2025-11-01T10:47:48.034673"
    },
    {
      "page_number": 16,
      "request_data": {
        "max_id": "WyJlYmVlMGJkMGI5YTY0N2JhODMxNTJmMDNlMTIxMTE1YSJd",
        "decoded_max_id": "ebee0bd0b9a647ba83152f03e121115a",
        "page": 1
      },
      "response": {
        "sections_count": 1,
        "more_available": true,
        "next_max_id": "ebee0bd0b9a647ba83152f03e121115a",
        "next_page": 2,
        "status": "ok"
      },
      "received_media_ids": [],
      "fetched_via_media_info": [],
      "raw_media_samples": [
        {
          "media_type": 2,
          "pk": 3754330683469525806,
          "id": "3754330683469525806_78243770695",
          "has_play_count": true,
          "has_view_count": false,
          "has_video_view_count": false,
          "play_count": 0,
          "view_count": null,
          "video_view_count": null
        },
        {
          "media_type": 2,
          "pk": 3755607405900905536,
          "id": "3755607405900905536_77719357247",
          "has_play_count": true,
          "has_view_count": false,
          "has_video_view_count": false,
          "play_count": 265,
          "view_count": null,
          "video_view_count": null
        }
      ],
      "timestamp": "2025-11-01T10:48:13.645762"
    }
  ],
  "last_update": "2025-11-01T10:48:13.653992"
}